[
    {
        "company": "深圳航空",
        "airline_code": "ZH9959",
        "start_drome": "深圳宝安国际机场",
        "arrive_drome": "北京首都国际机场",
        "start_time": "07:30",
        "arrive_time": "10:45",
        "mode": "739",
        "airline_stop": "0",
        "week": "123456日"
    },
    {
        "company": "中国国航",
        "airline_code": "CA3310",
        "start_drome": "深圳宝安国际机场",
        "arrive_drome": "北京首都国际机场",
        "start_time": "07:30",
        "arrive_time": "10:45",
        "mode": "739",
        "airline_stop": "0",
        "week": "123456日"
    },
    {
        "company": "海南航空",
        "airline_code": "HU7710",
        "start_drome": "深圳宝安国际机场",
        "arrive_drome": "北京首都国际机场",
        "start_time": "07:55",
        "arrive_time": "10:40",
        "mode": "333",
        "airline_stop": "0",
        "week": "123456日"
    },
    {
        "company": "南方航空",
        "airline_code": "CZ3151",
        "start_drome": "深圳宝安国际机场",
        "arrive_drome": "北京首都国际机场",
        "start_time": "08:30",
        "arrive_time": "11:35",
        "mode": "333",
        "airline_stop": "0",
        "week": "123456日"
    },
    {
        "company": "厦门航空",
        "airline_code": "MF1051",
        "start_drome": "深圳宝安国际机场",
        "arrive_drome": "北京首都国际机场",
        "start_time": "08:30",
        "arrive_time": "11:35",
        "mode": "333",
        "airline_stop": "0",
        "week": "123456日"
    },
    {
        "company": "深圳航空",
        "airline_code": "ZH1306",
        "start_drome": "深圳宝安国际机场",
        "arrive_drome": "北京首都国际机场",
        "start_time": "08:55",
        "arrive_time": "12:05",
        "mode": "JET",
        "airline_stop": "0",
        "week": "12346日"
    },
    {
        "company": "中国国航",
        "airline_code": "CA1306",
        "start_drome": "深圳宝安国际机场",
        "arrive_drome": "北京首都国际机场",
        "start_time": "08:55",
        "arrive_time": "12:05",
        "mode": "JET",
        "airline_stop": "0",
        "week": "12346日"
    },
    {
        "company": "深圳航空",
        "airline_code": "ZH1308",
        "start_drome": "深圳宝安国际机场",
        "arrive_drome": "北京首都国际机场",
        "start_time": "09:50",
        "arrive_time": "13:05",
        "mode": "330",
        "airline_stop": "0",
        "week": "1246"
    },
    {
        "company": "中国国航",
        "airline_code": "CA1308",
        "start_drome": "深圳宝安国际机场",
        "arrive_drome": "北京首都国际机场",
        "start_time": "09:50",
        "arrive_time": "13:05",
        "mode": "330",
        "airline_stop": "0",
        "week": "1246"
    },
    {
        "company": "深圳航空",
        "airline_code": "ZH9851",
        "start_drome": "深圳宝安国际机场",
        "arrive_drome": "北京首都国际机场",
        "start_time": "10:00",
        "arrive_time": "13:05",
        "mode": "739",
        "airline_stop": "0",
        "week": "123456日"
    },
    {
        "company": "中国国航",
        "airline_code": "CA3308",
        "start_drome": "深圳宝安国际机场",
        "arrive_drome": "北京首都国际机场",
        "start_time": "10:00",
        "arrive_time": "13:05",
        "mode": "739",
        "airline_stop": "0",
        "week": "123456日"
    },
    {
        "company": "南方航空",
        "airline_code": "CZ3159",
        "start_drome": "深圳宝安国际机场",
        "arrive_drome": "北京首都国际机场",
        "start_time": "10:30",
        "arrive_time": "13:35",
        "mode": "333",
        "airline_stop": "0",
        "week": "123456日"
    },
    {
        "company": "厦门航空",
        "airline_code": "MF1059",
        "start_drome": "深圳宝安国际机场",
        "arrive_drome": "北京首都国际机场",
        "start_time": "10:30",
        "arrive_time": "13:35",
        "mode": "333",
        "airline_stop": "0",
        "week": "123456日"
    },
    {
        "company": "东方航空",
        "airline_code": "MU3808",
        "start_drome": "深圳宝安国际机场",
        "arrive_drome": "北京南苑机场",
        "start_time": "11:55",
        "arrive_time": "15:00",
        "mode": "737",
        "airline_stop": "0",
        "week": "246"
    },
    {
        "company": "中国联航",
        "airline_code": "KN5852",
        "start_drome": "深圳宝安国际机场",
        "arrive_drome": "北京南苑机场",
        "start_time": "11:55",
        "arrive_time": "15:00",
        "mode": "737",
        "airline_stop": "0",
        "week": "246"
    },
    {
        "company": "南方航空",
        "airline_code": "CZ3193",
        "start_drome": "深圳宝安国际机场",
        "arrive_drome": "北京首都国际机场",
        "start_time": "12:15",
        "arrive_time": "15:30",
        "mode": "333",
        "airline_stop": "0",
        "week": "123456日"
    },
    {
        "company": "厦门航空",
        "airline_code": "MF1089",
        "start_drome": "深圳宝安国际机场",
        "arrive_drome": "北京首都国际机场",
        "start_time": "12:15",
        "arrive_time": "15:30",
        "mode": "333",
        "airline_stop": "0",
        "week": "123456日"
    },
    {
        "company": "深圳航空",
        "airline_code": "ZH9801",
        "start_drome": "深圳宝安国际机场",
        "arrive_drome": "北京首都国际机场",
        "start_time": "12:30",
        "arrive_time": "15:35",
        "mode": "739",
        "airline_stop": "0",
        "week": "123456日"
    },
    {
        "company": "中国国航",
        "airline_code": "CA3302",
        "start_drome": "深圳宝安国际机场",
        "arrive_drome": "北京首都国际机场",
        "start_time": "12:30",
        "arrive_time": "15:35",
        "mode": "739",
        "airline_stop": "0",
        "week": "123456日"
    },
    {
        "company": "海南航空",
        "airline_code": "HU7704",
        "start_drome": "深圳宝安国际机场",
        "arrive_drome": "北京首都国际机场",
        "start_time": "12:50",
        "arrive_time": "16:00",
        "mode": "738",
        "airline_stop": "0",
        "week": "123456日"
    },
    {
        "company": "深圳航空",
        "airline_code": "ZH1338",
        "start_drome": "深圳宝安国际机场",
        "arrive_drome": "北京首都国际机场",
        "start_time": "12:50",
        "arrive_time": "16:00",
        "mode": "JET",
        "airline_stop": "0",
        "week": "123456"
    },
    {
        "company": "深圳航空",
        "airline_code": "ZH1338",
        "start_drome": "深圳宝安国际机场",
        "arrive_drome": "北京首都国际机场",
        "start_time": "12:50",
        "arrive_time": "16:00",
        "mode": "JET",
        "airline_stop": "0",
        "week": "6日"
    },
    {
        "company": "中国国航",
        "airline_code": "CA1338",
        "start_drome": "深圳宝安国际机场",
        "arrive_drome": "北京首都国际机场",
        "start_time": "12:50",
        "arrive_time": "16:00",
        "mode": "JET",
        "airline_stop": "0",
        "week": "123456"
    },
    {
        "company": "中国国航",
        "airline_code": "CA1338",
        "start_drome": "深圳宝安国际机场",
        "arrive_drome": "北京首都国际机场",
        "start_time": "12:50",
        "arrive_time": "16:00",
        "mode": "JET",
        "airline_stop": "0",
        "week": "6日"
    },
    {
        "company": "南方航空",
        "airline_code": "CZ3153",
        "start_drome": "深圳宝安国际机场",
        "arrive_drome": "北京首都国际机场",
        "start_time": "13:30",
        "arrive_time": "16:35",
        "mode": "333",
        "airline_stop": "0",
        "week": "123456日"
    },
    {
        "company": "厦门航空",
        "airline_code": "MF1053",
        "start_drome": "深圳宝安国际机场",
        "arrive_drome": "北京首都国际机场",
        "start_time": "13:30",
        "arrive_time": "16:35",
        "mode": "333",
        "airline_stop": "0",
        "week": "123456日"
    },
    {
        "company": "南方航空",
        "airline_code": "CZ3255",
        "start_drome": "深圳宝安国际机场",
        "arrive_drome": "北京首都国际机场",
        "start_time": "13:50",
        "arrive_time": "19:10",
        "mode": "320",
        "airline_stop": "0",
        "week": "246"
    },
    {
        "company": "厦门航空",
        "airline_code": "MF1147",
        "start_drome": "深圳宝安国际机场",
        "arrive_drome": "北京首都国际机场",
        "start_time": "13:50",
        "arrive_time": "19:10",
        "mode": "320",
        "airline_stop": "0",
        "week": "246"
    },
    {
        "company": "深圳航空",
        "airline_code": "ZH1368",
        "start_drome": "深圳宝安国际机场",
        "arrive_drome": "北京首都国际机场",
        "start_time": "14:00",
        "arrive_time": "17:05",
        "mode": "JET",
        "airline_stop": "0",
        "week": "16"
    },
    {
        "company": "中国国航",
        "airline_code": "CA1368",
        "start_drome": "深圳宝安国际机场",
        "arrive_drome": "北京首都国际机场",
        "start_time": "14:00",
        "arrive_time": "17:05",
        "mode": "JET",
        "airline_stop": "0",
        "week": "16"
    },
    {
        "company": "深圳航空",
        "airline_code": "ZH1384",
        "start_drome": "深圳宝安国际机场",
        "arrive_drome": "北京首都国际机场",
        "start_time": "15:00",
        "arrive_time": "18:05",
        "mode": "JET",
        "airline_stop": "0",
        "week": "123456日"
    },
    {
        "company": "深圳航空",
        "airline_code": "ZH9831",
        "start_drome": "深圳宝安国际机场",
        "arrive_drome": "北京首都国际机场",
        "start_time": "15:00",
        "arrive_time": "18:15",
        "mode": "739",
        "airline_stop": "0",
        "week": "123456日"
    },
    {
        "company": "中国国航",
        "airline_code": "CA1384",
        "start_drome": "深圳宝安国际机场",
        "arrive_drome": "北京首都国际机场",
        "start_time": "15:00",
        "arrive_time": "18:05",
        "mode": "JET",
        "airline_stop": "0",
        "week": "123456日"
    },
    {
        "company": "中国国航",
        "airline_code": "CA3306",
        "start_drome": "深圳宝安国际机场",
        "arrive_drome": "北京首都国际机场",
        "start_time": "15:00",
        "arrive_time": "18:15",
        "mode": "739",
        "airline_stop": "0",
        "week": "123456日"
    },
    {
        "company": "东方航空",
        "airline_code": "MU3810",
        "start_drome": "深圳宝安国际机场",
        "arrive_drome": "北京南苑机场",
        "start_time": "15:25",
        "arrive_time": "18:25",
        "mode": "737",
        "airline_stop": "0",
        "week": "123456日"
    },
    {
        "company": "中国联航",
        "airline_code": "KN5856",
        "start_drome": "深圳宝安国际机场",
        "arrive_drome": "北京南苑机场",
        "start_time": "15:25",
        "arrive_time": "18:25",
        "mode": "737",
        "airline_stop": "0",
        "week": "123456日"
    },
    {
        "company": "南方航空",
        "airline_code": "CZ3189",
        "start_drome": "深圳宝安国际机场",
        "arrive_drome": "北京首都国际机场",
        "start_time": "15:50",
        "arrive_time": "19:00",
        "mode": "333",
        "airline_stop": "0",
        "week": "46日"
    },
    {
        "company": "厦门航空",
        "airline_code": "MF1085",
        "start_drome": "深圳宝安国际机场",
        "arrive_drome": "北京首都国际机场",
        "start_time": "15:50",
        "arrive_time": "19:00",
        "mode": "333",
        "airline_stop": "0",
        "week": "46日"
    },
    {
        "company": "深圳航空",
        "airline_code": "ZH1314",
        "start_drome": "深圳宝安国际机场",
        "arrive_drome": "北京首都国际机场",
        "start_time": "16:00",
        "arrive_time": "19:05",
        "mode": "JET",
        "airline_stop": "0",
        "week": "1346"
    },
    {
        "company": "中国国航",
        "airline_code": "CA1314",
        "start_drome": "深圳宝安国际机场",
        "arrive_drome": "北京首都国际机场",
        "start_time": "16:00",
        "arrive_time": "19:05",
        "mode": "JET",
        "airline_stop": "0",
        "week": "1346"
    },
    {
        "company": "海南航空",
        "airline_code": "HU7708",
        "start_drome": "深圳宝安国际机场",
        "arrive_drome": "北京首都国际机场",
        "start_time": "16:20",
        "arrive_time": "19:25",
        "mode": "333",
        "airline_stop": "0",
        "week": "123456日"
    },
    {
        "company": "深圳航空",
        "airline_code": "ZH9821",
        "start_drome": "深圳宝安国际机场",
        "arrive_drome": "北京首都国际机场",
        "start_time": "16:25",
        "arrive_time": "19:35",
        "mode": "739",
        "airline_stop": "0",
        "week": "123456日"
    },
    {
        "company": "中国国航",
        "airline_code": "CA3304",
        "start_drome": "深圳宝安国际机场",
        "arrive_drome": "北京首都国际机场",
        "start_time": "16:25",
        "arrive_time": "19:35",
        "mode": "739",
        "airline_stop": "0",
        "week": "123456日"
    },
    {
        "company": "深圳航空",
        "airline_code": "ZH9969",
        "start_drome": "深圳宝安国际机场",
        "arrive_drome": "北京首都国际机场",
        "start_time": "17:10",
        "arrive_time": "20:25",
        "mode": "738",
        "airline_stop": "0",
        "week": "123456日"
    },
    {
        "company": "中国国航",
        "airline_code": "CA3527",
        "start_drome": "深圳宝安国际机场",
        "arrive_drome": "北京首都国际机场",
        "start_time": "17:10",
        "arrive_time": "20:25",
        "mode": "738",
        "airline_stop": "0",
        "week": "123456日"
    },
    {
        "company": "南方航空",
        "airline_code": "CZ3191",
        "start_drome": "深圳宝安国际机场",
        "arrive_drome": "北京首都国际机场",
        "start_time": "17:30",
        "arrive_time": "21:00",
        "mode": "333",
        "airline_stop": "0",
        "week": "123456日"
    },
    {
        "company": "厦门航空",
        "airline_code": "MF1087",
        "start_drome": "深圳宝安国际机场",
        "arrive_drome": "北京首都国际机场",
        "start_time": "17:30",
        "arrive_time": "21:00",
        "mode": "333",
        "airline_stop": "0",
        "week": "123456日"
    },
    {
        "company": "深圳航空",
        "airline_code": "ZH1304",
        "start_drome": "深圳宝安国际机场",
        "arrive_drome": "北京首都国际机场",
        "start_time": "18:00",
        "arrive_time": "21:10",
        "mode": "JET",
        "airline_stop": "0",
        "week": "16"
    },
    {
        "company": "中国国航",
        "airline_code": "CA1304",
        "start_drome": "深圳宝安国际机场",
        "arrive_drome": "北京首都国际机场",
        "start_time": "18:00",
        "arrive_time": "21:10",
        "mode": "JET",
        "airline_stop": "0",
        "week": "16"
    },
    {
        "company": "深圳航空",
        "airline_code": "ZH9582",
        "start_drome": "深圳宝安国际机场",
        "arrive_drome": "北京首都国际机场",
        "start_time": "18:45",
        "arrive_time": "23:35",
        "mode": "320",
        "airline_stop": "0",
        "week": "123456日"
    },
    {
        "company": "海南航空",
        "airline_code": "HU7706",
        "start_drome": "深圳宝安国际机场",
        "arrive_drome": "北京首都国际机场",
        "start_time": "19:00",
        "arrive_time": "22:05",
        "mode": "738",
        "airline_stop": "0",
        "week": "123456日"
    },
    {
        "company": "深圳航空",
        "airline_code": "ZH1398",
        "start_drome": "深圳宝安国际机场",
        "arrive_drome": "北京首都国际机场",
        "start_time": "19:15",
        "arrive_time": "22:20",
        "mode": "330",
        "airline_stop": "0",
        "week": "12346"
    },
    {
        "company": "中国国航",
        "airline_code": "CA1398",
        "start_drome": "深圳宝安国际机场",
        "arrive_drome": "北京首都国际机场",
        "start_time": "19:15",
        "arrive_time": "22:20",
        "mode": "330",
        "airline_stop": "0",
        "week": "12346"
    },
    {
        "company": "南方航空",
        "airline_code": "CZ3155",
        "start_drome": "深圳宝安国际机场",
        "arrive_drome": "北京首都国际机场",
        "start_time": "19:55",
        "arrive_time": "23:00",
        "mode": "333",
        "airline_stop": "0",
        "week": "123456日"
    },
    {
        "company": "厦门航空",
        "airline_code": "MF1055",
        "start_drome": "深圳宝安国际机场",
        "arrive_drome": "北京首都国际机场",
        "start_time": "19:55",
        "arrive_time": "23:00",
        "mode": "333",
        "airline_stop": "0",
        "week": "123456日"
    },
    {
        "company": "深圳航空",
        "airline_code": "ZH1358",
        "start_drome": "深圳宝安国际机场",
        "arrive_drome": "北京首都国际机场",
        "start_time": "20:00",
        "arrive_time": "23:05",
        "mode": "JET",
        "airline_stop": "0",
        "week": "146日"
    },
    {
        "company": "中国国航",
        "airline_code": "CA1358",
        "start_drome": "深圳宝安国际机场",
        "arrive_drome": "北京首都国际机场",
        "start_time": "20:00",
        "arrive_time": "23:05",
        "mode": "JET",
        "airline_stop": "0",
        "week": "146日"
    },
    {
        "company": "深圳航空",
        "airline_code": "ZH9890",
        "start_drome": "深圳宝安国际机场",
        "arrive_drome": "北京首都国际机场",
        "start_time": "20:45",
        "arrive_time": "23:50",
        "mode": "739",
        "airline_stop": "0",
        "week": "123456日"
    },
    {
        "company": "中国国航",
        "airline_code": "CA3312",
        "start_drome": "深圳宝安国际机场",
        "arrive_drome": "北京首都国际机场",
        "start_time": "20:45",
        "arrive_time": "23:50",
        "mode": "739",
        "airline_stop": "0",
        "week": "123456日"
    },
    {
        "company": "深圳航空",
        "airline_code": "ZH9968",
        "start_drome": "深圳宝安国际机场",
        "arrive_drome": "北京首都国际机场",
        "start_time": "21:00",
        "arrive_time": "00:15",
        "mode": "738",
        "airline_stop": "0",
        "week": "123456日"
    },
    {
        "company": "中国国航",
        "airline_code": "CA3390",
        "start_drome": "深圳宝安国际机场",
        "arrive_drome": "北京首都国际机场",
        "start_time": "21:00",
        "arrive_time": "00:15",
        "mode": "738",
        "airline_stop": "0",
        "week": "123456日"
    },
    {
        "company": "海南航空",
        "airline_code": "HU7702",
        "start_drome": "深圳宝安国际机场",
        "arrive_drome": "北京首都国际机场",
        "start_time": "21:15",
        "arrive_time": "00:25",
        "mode": "738",
        "airline_stop": "0",
        "week": "123456日"
    },
    {
        "company": "南方航空",
        "airline_code": "CZ3962",
        "start_drome": "深圳宝安国际机场",
        "arrive_drome": "北京首都国际机场",
        "start_time": "21:30",
        "arrive_time": "00:30",
        "mode": "333",
        "airline_stop": "0",
        "week": "123456日"
    },
    {
        "company": "厦门航空",
        "airline_code": "MF1816",
        "start_drome": "深圳宝安国际机场",
        "arrive_drome": "北京首都国际机场",
        "start_time": "21:30",
        "arrive_time": "00:30",
        "mode": "333",
        "airline_stop": "0",
        "week": "123456日"
    },
    {
        "company": "深圳航空",
        "airline_code": "ZH1896",
        "start_drome": "深圳宝安国际机场",
        "arrive_drome": "北京首都国际机场",
        "start_time": "21:45",
        "arrive_time": "00:45",
        "mode": "JET",
        "airline_stop": "0",
        "week": "123456日"
    },
    {
        "company": "中国国航",
        "airline_code": "CA1896",
        "start_drome": "深圳宝安国际机场",
        "arrive_drome": "北京首都国际机场",
        "start_time": "21:45",
        "arrive_time": "00:45",
        "mode": "JET",
        "airline_stop": "0",
        "week": "123456日"
    }
]